darwinian/__init__.py
darwinian/darwinian.py
examples/backpack.py
examples/maximum_and_minimum.py
examples/shortest_path.py
Darwinian-0.0.5.4.dist-info/LICENSE
Darwinian-0.0.5.4.dist-info/METADATA
Darwinian-0.0.5.4.dist-info/WHEEL
Darwinian-0.0.5.4.dist-info/top_level.txt
Darwinian-0.0.5.4.dist-info/RECORD
