Metadata-Version: 2.1
Name: Darwinian
Version: 0.0.5.4
Summary: “Darwinian” - это модуль Python, который реализует Дарвиновский Генетический Алгоритм (GA) для задач оптимизации. GA симулирует процесс естественного отбора, где наиболее приспособленные особи выбираются для воспроизводства, чтобы произвести потомство следующего поколения.
Author-email: Arseniy Vinner <mrliquidxd@gmail.com>
Project-URL: Homepage, https://github.com/MrLiquidXd/Darwinian-GA
Project-URL: Issues, https://github.com/MrLiquidXd/Darwinian-GA/issues
Classifier: Programming Language :: Python :: 3
Classifier: License :: OSI Approved :: MIT License
Classifier: Operating System :: OS Independent
Requires-Python: >=3.9
License-File: LICENSE
